pyface/__init__.py
pyface/face_service.py
pyface/object.py
pyface/utils.py
pyface/components/__init__.py
pyface/components/enums.py
pyface/components/face_gender.py
pyface/components/face_normalization.py
pyface/components/utils.py
pyface/components/face_depth/__init__.py
pyface/components/face_depth/tddfav2.py
pyface/components/face_depth/Sim3DR/rasterize.cpp
pyface/components/face_depth/Sim3DR/rasterize.h
pyface/components/face_depth/Sim3DR/rasterize.pyx
pyface/components/face_depth/Sim3DR/rasterize_kernel.cpp
pyface/components/face_depth/Sim3DR/sim3dr_cython.cpython-310-x86_64-linux-gnu.so
pyface/components/face_detection/__init__.py
pyface/components/face_detection/draw.py
pyface/components/face_detection/nms.py
pyface/components/face_detection/scrfd.py
pyface/components/face_landmark/__init__.py
pyface/components/face_landmark/coordinate_reg.py
pyface/components/face_landmark/utils.py
pyface/components/face_recognition/__init__.py
pyface/components/face_recognition/arcface.py
pyface/components/face_recognition/compare.py
pyface/components/face_recognition/utils.py
pyface_docsaid-0.4.0.dist-info/METADATA
pyface_docsaid-0.4.0.dist-info/WHEEL
pyface_docsaid-0.4.0.dist-info/top_level.txt
pyface_docsaid-0.4.0.dist-info/RECORD
pyface_docsaid-0.4.0.dist-info/licenses/LICENSE
