Metadata-Version: 2.4
Name: pyface-docsaid
Version: 0.4.0
Summary: An Integrated Python Package for Face Analysis.
Author-email: kunkunlin <jacklin@cmlab.csie.ntu.edu.tw>
License: Apache License 2.0
Project-URL: Homepage, https://github.com/DocsaidLab/PyFace
Project-URL: Repository, https://github.com/DocsaidLab/PyFace
Project-URL: Issues, https://github.com/DocsaidLab/PyFace/issues
Classifier: Development Status :: 5 - Production/Stable
Classifier: License :: OSI Approved :: Apache Software License
Classifier: Intended Audience :: Developers
Classifier: Intended Audience :: Science/Research
Classifier: Operating System :: OS Independent
Classifier: Programming Language :: Python :: 3.10
Classifier: Programming Language :: Python :: 3.12
Classifier: Topic :: Software Development :: Libraries
Classifier: Topic :: Software Development :: Libraries :: Python Modules
Requires-Python: >=3.10
License-File: LICENSE
Requires-Dist: numpy>=2
Requires-Dist: scikit-image
Requires-Dist: capybara-docsaid>=0.12.0
Requires-Dist: huggingface_hub
Dynamic: license-file
